[
 {
  "css": "/* General Page Setup */\r\n\r\n\r\n.print-format {\r\n  font-family: \"Helvetica\", \"Arial\", sans-serif;\r\n  font-size: 12px;\r\n  color: #333;\r\n  line-height: 1.4;\r\n  padding: 20px;\r\n  margin: 0 -3mm;\r\n\r\n}\r\n\r\n\r\n\r\n.print-heading{\r\nborder-bottom:none;\r\nposition:relative;\r\ntop:1cm;\r\n\r\n}\r\n\r\n.print-heading h2 {\r\n  text-align: left;\r\n  font-size: 20px;\r\n  margin: 0;\r\n  color: #222;\r\n}\r\n.print-heading .sub-heading {\r\n  display: block;\r\n  font-size: 13px;\r\n  color: #777;\r\n  margin-top: 4px;\r\n}\r\n\r\n/* Section Titles */\r\n.section-break label {\r\n  font-weight: bold;\r\n  color: #444;\r\n}\r\n\r\n/* Data Rows */\r\n.data-field {\r\n  margin: 4px 0;\r\n  font-size: 12px;\r\n}\r\n.data-field label {\r\n  font-weight: 600;\r\n  color: #555;\r\n}\r\n.data-field .value {\r\n  font-weight: 500;\r\n  color: #222;\r\n}\r\n\r\n/* Two-column Layout Fix */\r\n.column-break {\r\n  padding: 5px 10px;\r\n}\r\n\r\n/* Summary Section in one line */\r\n/* Make the summary section inline */\r\n\r\n/* Make each data-field inline with no gaps */\r\n[data-label=\"Summary\"] .data-field {\r\n    display: flex;\r\n    flex-wrap: nowrap;        /* prevent label from breaking into 2 lines */\r\n    align-items: center;      /* align label + value vertically */\r\n    gap: 2px;                 /* small space between label and value */\r\n    white-space: nowrap;\r\n    margin-left:0.4cm;/* force text to stay in one line */\r\n}\r\n\r\n/* Reset the inner col-xs-12 blocks */\r\n[data-label=\"Summary\"] .data-field .col-xs-12 {\r\n    display: inline; \r\n    width: auto !important;\r\n    padding: 0 !important;\r\n    margin: 0 !important;\r\n}\r\n\r\n/* Styling */\r\n[data-label=\"Summary\"] .data-field label {\r\n    font-weight: bold;\r\n    margin: 0;\r\n}\r\n\r\n[data-label=\"Summary\"] .data-field .value {\r\n    font-weight: normal;\r\n    margin-left: 0.2cm !important;\r\n}\r\n\r\n\r\n\r\n[data-fieldname=\"naming_series\"] {\r\n  display:none !important;\r\n}\r\n\r\n[data-fieldname=\"custom_barcode\"] .col-xs-7  {\r\nposition:relative;\r\nbottom:1cm;\r\n  width:70%;\r\n  height:20%;\r\n \r\n}\r\n[data-fieldname=\"driver\"]  {\r\nposition:relative;\r\nbottom:1.5cm;\r\n \r\n}\r\n\r\n\r\n\r\n[data-fieldname=\"custom_barcode\"] .col-xs-5 {\r\n  display:none;\r\n  \r\n                 \r\n}\r\n\r\n\r\n/* Table Styling */\r\ntable {\r\n  width: 100%;\r\n  border-collapse: collapse;\r\n  margin-top: 10px;\r\n}\r\ntable thead th {\r\n  background: #f2f2f2;\r\n  font-weight: bold;\r\n  text-align: center;\r\n  border: 1px solid #ccc;\r\n  padding: 6px;\r\n  font-size: 12px;\r\n}\r\ntable tbody td {\r\n  border: 1px solid #ccc;\r\n  padding: 6px;\r\n  font-size: 12px;\r\n}\r\n.table-sr {\r\n  text-align: center;\r\n  font-weight: 600;\r\n}\r\n.text-right {\r\n  text-align: right;\r\n}\r\n\r\n/* Footer Page Numbers */\r\n#footer-html {\r\n  border-top: 1px solid #ccc;\r\n  margin-top: 20px;\r\n  padding-top: 8px;\r\n}\r\n#footer-html .page-number {\r\n  font-size: 11px;\r\n  color: #777;\r\n}\r\n\r\n#footer-html {\r\n  border-top: 1px solid #ccc;\r\n  margin-top: 20px;\r\n  padding-top: 8px;\r\n  page-break-after: avoid !important;\r\n}\r\n\r\n.print-format .page-break:last-child {\r\n  page-break-after: auto !important;\r\n}\r\n\r\n\r\n[data-fieldname=\"workflow_state\"] {\r\n  display: none !important;\r\n}\r\n\r\n[data-fieldname=\"_last_child_rows\"] {\r\n  display: none !important;\r\n}\r\n\r\n[data-fieldname=\"delivery_route_item\"] {\r\n  text-align:center !important;\r\n}\r\n\r\n\r\n\r\n\r\n[data-fieldname=\"route_name\"] label {\r\n  color: transparent !important;   /* make original text invisible */\r\n  position: relative;\r\n}\r\n\r\n[data-fieldname=\"route_name\"] label::after {\r\n  content: \"Route Name:\"; \r\n  position: absolute;\r\n  left: 0; \r\n  top: 0;\r\n  color: #444 !important;          /* visible replacement text */\r\n  font-size: 12px;\r\n  font-weight: bold;\r\n}\r\n\r\n\r\nth.table-sr {\r\npadding-left:0.5cm!important;\r\n  text-align: center;\r\n}\r\n\r\nth.table-sr::before {\r\n  content: \"#\";\r\n}\r\n\r\nth.table-sr {\r\n  color: transparent !important; /* hide \"Sr\" text itself */\r\n}\r\n\r\nth.text-right {\r\n    position: relative;       /* make positioning work */\r\n    color: transparent;       /* hide original text */\r\n    background-color: transparent !important;\r\n}\r\n\r\nth.text-right::after {\r\n    content: \"Packs\";  /* new text */\r\n    position: absolute;\r\n    left: 0;\r\n    top: 0.25cm;\r\n    width: 70%;\r\n    height: 100%;\r\n    color: #000;              /* visible color */\r\n    text-align: right;        /* same as original alignment */\r\n    font-weight: bold;        /* match table header style */\r\n    display: flex;\r\n    align-items: center;      /* vertically center */\r\n    justify-content: flex-end; /* right align */\r\n    padding-right: 6px;       /* match table padding */\r\n    \r\n}\r\n\r\n\r\n",
  "disabled": 0,
  "docstatus": 0,
  "doctype": "Print Style",
  "modified": "2025-09-19 10:44:32.703963",
  "name": "Print Style Delivery Route",
  "preview": null,
  "print_style_name": "Print Style Delivery Route",
  "standard": 0
 }
]
